nextflix/__init__.py
nextflix/models.py
nextflix/views.py
nextflix-1.0.0.dist-info/METADATA
nextflix-1.0.0.dist-info/WHEEL
nextflix-1.0.0.dist-info/top_level.txt
nextflix-1.0.0.dist-info/RECORD
