Metadata-Version: 2.1
Name: nextflix
Version: 1.0.0
Summary: A new way to to watch movies online without paying anything
Home-page: UNKNOWN
License: UNKNOWN
Platform: UNKNOWN
